space_simulator/__init__.py
space_simulator/constants.py
space_simulator/debug.py
space_simulator/game.py
space_simulator/sat.py
space_simulator-0.2.1.dist-info/entry_points.txt
space_simulator-0.2.1.dist-info/WHEEL
space_simulator-0.2.1.dist-info/METADATA
space_simulator-0.2.1.dist-info/RECORD
