Metadata-Version: 2.1
Name: space-simulator
Version: 0.2.1
Summary: 
Author: Tamles
Author-email: methacrylon@gmail.com
Requires-Python: >=3.9,<4.0
Classifier: Programming Language :: Python :: 3
Classifier: Programming Language :: Python :: 3.9
Classifier: Programming Language :: Python :: 3.10
Requires-Dist: arcade (>=2.6.16,<3.0.0)
Requires-Dist: numpy (>=1.23.4,<2.0.0)
Requires-Dist: scipy (>=1.9.3,<2.0.0)
